tesseract_window_scanner/LICENSE
tesseract_window_scanner/README.MD
tesseract_window_scanner/__init__.py
tesseract_window_scanner/requirements.txt
tesseract_window_scanner/thirdparty.json
tesseract_window_scanner-0.12.dist-info/LICENSE.rst
tesseract_window_scanner-0.12.dist-info/METADATA
tesseract_window_scanner-0.12.dist-info/WHEEL
tesseract_window_scanner-0.12.dist-info/top_level.txt
tesseract_window_scanner-0.12.dist-info/RECORD
