Metadata-Version: 2.1
Name: tesseract-window-scanner
Version: 0.12
Summary: OCR on screenshots with tesseract - Windows only
Home-page: https://github.com/hansalemaos/tesseract_window_scanner
Author: Johannes Fischer
Author-email: <aulasparticularesdealemaosp@gmail.com>
License: MIT
Keywords: screenshot,adb,windows,hwnd,handle,bot,tesseract
Classifier: Development Status :: 4 - Beta
Classifier: Programming Language :: Python :: 3 :: Only
Classifier: Programming Language :: Python :: 3.9
Classifier: Topic :: Scientific/Engineering :: Visualization
Classifier: Topic :: Software Development :: Libraries :: Python Modules
Classifier: Topic :: Text Editors :: Text Processing
Classifier: Topic :: Text Processing :: General
Classifier: Topic :: Text Processing :: Indexing
Classifier: Topic :: Text Processing :: Filters
Classifier: Topic :: Utilities
License-File: LICENSE.rst
Requires-Dist: a-pandas-ex-tesseract-multirow-regex-fuzz
Requires-Dist: keyboard
Requires-Dist: numpy
Requires-Dist: opencv-python
Requires-Dist: pandas
Requires-Dist: windows-adb-screen-capture
